<annotation>
	<folder>Unobstructed_Resized</folder>
	<filename>scene_extraced01461.jpg</filename>
	<path>C:\Users\abm0406\Desktop\Image dump\Unobstructed\Unobstructed_Resized\scene_extraced01461.jpg</path>
	<source>
		<database>Unknown</database>
	</source>
	<size>
		<width>300</width>
		<height>300</height>
		<depth>3</depth>
	</size>
	<segmented>0</segmented>
	<object>
		<name>Dumpster</name>
		<pose>Unspecified</pose>
		<truncated>0</truncated>
		<difficult>0</difficult>
		<bndbox>
			<xmin>83</xmin>
			<ymin>77</ymin>
			<xmax>294</xmax>
			<ymax>180</ymax>
		</bndbox>
	</object>
</annotation>
